sampley/__init__.py
sampley/auxiliary.py
sampley/classes.py
sampley/functions.py
sampley-0.0.15.dist-info/licenses/LICENSE
sampley-0.0.15.dist-info/METADATA
sampley-0.0.15.dist-info/WHEEL
sampley-0.0.15.dist-info/top_level.txt
sampley-0.0.15.dist-info/RECORD
