Metadata-Version: 2.4
Name: sampley
Version: 0.0.15
Summary: sample survey data
Author: <temporarily redacted>
License-Expression: MIT
Project-URL: Homepage, https://github.com/JSBigelow/sampley
Project-URL: Repository, https://github.com/JSBigelow/sampley
Project-URL: UserManual, https://github.com/JSBigelow/sampley/blob/main/sampley%20-%20User%20Manual.pdf
Project-URL: Exemplars, https://github.com/JSBigelow/sampley/tree/main/exemplars
Classifier: Programming Language :: Python :: 3
Requires-Python: >=3.8
License-File: LICENSE
Requires-Dist: geopandas>=1.0.0
Requires-Dist: matplotlib>=3.0.0
Requires-Dist: numpy>=1.26.4
Requires-Dist: pandas>=2.0.0
Requires-Dist: pyogrio
Requires-Dist: pyproj>=3.0.0
Requires-Dist: pytz>=2024.1
Requires-Dist: scipy>=1.0.0
Requires-Dist: shapely>=2.0.0
Requires-Dist: thinst>=0.0.8
Requires-Dist: matplotlib>=3.0.0
Dynamic: license-file
